tasks/riscv-task/riscv-task/data_memory.sv
import common_pkg::*;

module data_memory (clk, rst, w_data, r_data, address, ctrl_mem_w, ctrl_mem_r);

  input                                     clk;
  input                                     rst;
  input                                     ctrl_mem_w;
  input                                     ctrl_mem_r;
  input [RISC_V_DATA_WIDTH - 1 : 0]         w_data;
  input [DATA_MEMORY_ADDRESS_WIDTH - 1 : 0] address;

  output reg [RISC_V_DATA_WIDTH - 1 : 0]    r_data;


  reg [RISC_V_DATA_WIDTH - 1 : 0]  rom_memory  [DATA_MEMORY_ROM_DEPTH];
  reg [RISC_V_DATA_WIDTH - 1 : 0]  ram_memory  [DATA_MEMORY_RAM_DEPTH];


  integer i;

  initial begin
    $readmemh(  "data_memory.mem",
              rom_memory, 
              DATA_MEMORY_ADDRESS_WIDTH'('h0),
              DATA_MEMORY_ADDRESS_WIDTH'('hFF)); // load ROM memory


    for (i = 0; i < DATA_MEMORY_RAM_DEPTH; i = i + 1) ram_memory[i] = RISC_V_DATA_WIDTH'('b0); // initialize RAM
  end


  always @(*) begin
    // --------------------reading ROM and RAM -----------------------
    if (ctrl_mem_r) begin
      if (address < DATA_MEMORY_ROM_DEPTH) begin
        r_data = rom_memory[address];
      end else begin
        r_data = ram_memory[address - DATA_MEMORY_ROM_DEPTH];
      end
    end else begin
      r_data = RISC_V_DATA_WIDTH'('b0);
    end
    // -------------------------------------------
  end

  always @(posedge clk or posedge rst) begin
    if (rst) begin
      // --------------set RAM entries to zero -----------------------------
      for (i = 0; i < DATA_MEMORY_RAM_DEPTH; i = i + 1) begin
        ram_memory[i] <= RISC_V_DATA_WIDTH'('b0);
      end
      // -------------------------------------------
    end else begin
      // ---------------write data to RAM if write signal is set and address is a valid RAM address----------------------------
      if (ctrl_mem_w && (address >= DATA_MEMORY_ROM_DEPTH)) begin
        ram_memory[address - DATA_MEMORY_ROM_DEPTH] <= w_data;
      end
      // -------------------------------------------
    end
  end

endmodule

tasks/riscv-task/riscv-task/ALU.sv
import common_pkg::*;

module ALU (data_in_A, data_in_B, data_out, zero, ALU_ctrl);

  input  signed [RISC_V_DATA_WIDTH - 1 : 0]  data_in_A;
  input  signed [RISC_V_DATA_WIDTH - 1 : 0]  data_in_B;
  input         ALU_ctrl_t                   ALU_ctrl;

  output signed [RISC_V_DATA_WIDTH - 1 : 0]  data_out;
  output                                     zero;

  reg signed [RISC_V_DATA_WIDTH - 1 : 0] result;


  assign data_out = result;

  // -------------------zero flag---------------------
  assign zero = (result == 0);
  // -------------------------------------------

  always @(*)
    begin
      case (ALU_ctrl)
        // -------------------------------------------
        AND: result = data_in_A & data_in_B;
        OR:  result = data_in_A | data_in_B;
        ADD: result = data_in_A + data_in_B;
        SUB: result = data_in_A - data_in_B;
        // -------------------------------------------
        default: result = RISC_V_DATA_WIDTH'('b0);
      endcase
    end

endmodule

tasks/riscv-task/riscv-task/ALU_control.sv
import common_pkg::*;

module ALU_control (

  funct3,
  funct7,

  ALU_ctrl,

  ctrl_ALU_op

);

  input [2:0] funct3;
  input [6:0] funct7;

  input [1:0] ctrl_ALU_op;

  output  ALU_ctrl_t  ALU_ctrl;

  always @(*)
    begin
      case (ctrl_ALU_op)
        2'b00   : ALU_ctrl = ADD; // ld/sd
        2'b01   : ALU_ctrl = SUB; // beq
        2'b10   : begin
          if (funct7 == 7'b0000000 && funct3 == 3'b000)       ALU_ctrl = ADD; // add
          else if (funct7 == 7'b0100000 && funct3 == 3'b000)  ALU_ctrl = SUB; // sub
          else if (funct7 == 7'b0000000 && funct3 == 3'b111)  ALU_ctrl = AND; // and
          else if (funct7 == 7'b0000000 && funct3 == 3'b110)  ALU_ctrl = OR;  // or
          else                                                ALU_ctrl = AND; // default
        end
        default : ALU_ctrl = AND;
      endcase
    end

endmodule

tasks/riscv-task/riscv-task/imm_generator.sv
import common_pkg::*;

module imm_generator (
  instruction,
  offset
);

  input   logic           [INSTRUCTION_WIDTH - 1 : 0] instruction;
  output  logic signed    [RISC_V_DATA_WIDTH - 1 : 0] offset;

  opcode_t opcode;

  logic [11:0] imm;

  assign opcode = opcode_t'(instruction[6:0]);

  always_comb begin
    case (opcode)
      LOAD    : imm = instruction [31:20];
      STORE   : imm = {instruction[31:25], instruction [11:7]};
      BRANCH  : imm = {instruction[31], instruction[7], instruction[30:25], instruction[11:8]};

      default : imm = 12'b0;
    endcase
  end

  assign offset = { { (RISC_V_DATA_WIDTH-12){imm[11]} }, imm };

endmodule

tasks/riscv-task/riscv-task/register_file.sv
import common_pkg::*;

module register_file (clk, rst, reg_num_r0, reg_num_r1, reg_num_w, r_data_0, r_data_1, w_data,  ctrl_reg_w, debug);

  input                                       clk;                        // clock
  input                                       rst;                        // reset

  input [REGISTER_FILE_ADDRESS_WIDTH - 1 : 0] reg_num_r0;                 // register selection read 0
  input [REGISTER_FILE_ADDRESS_WIDTH - 1 : 0] reg_num_r1;                 // register selection read 1
  input [REGISTER_FILE_ADDRESS_WIDTH - 1 : 0] reg_num_w;                  // register selection write
  input [RISC_V_DATA_WIDTH - 1 : 0]           w_data;                     // write data input
  input                                       ctrl_reg_w;                 // Enables writing to registers on a clock edge

  output [RISC_V_DATA_WIDTH - 1 : 0]          r_data_0;                   // read data output 0
  output [RISC_V_DATA_WIDTH - 1 : 0]          r_data_1;                   // read data output 1
  output [15:0]                               debug;                      // debug port


  reg [RISC_V_DATA_WIDTH - 1 : 0] RF [REGISTER_FILE_NUM];                 // 32 individual 64-bit registers to be fetched

  integer i;

  initial begin
    for (i = 0; i < REGISTER_FILE_NUM; i = i + 1) RF[i] = RISC_V_DATA_WIDTH'('b0); // initialize registers
  end

  assign r_data_0 = RF[reg_num_r0];
  assign r_data_1 = RF[reg_num_r1];
  assign debug    = RF[31][15:0];

  always @(posedge clk or posedge rst) begin
    // ---------------reset and write functionality----------------------------
    if (rst) begin
        for (i = 0; i < REGISTER_FILE_NUM; i = i + 1) begin
            RF[i] <= RISC_V_DATA_WIDTH'('b0);
        end
    end else begin
        if (ctrl_reg_w) begin
            RF[reg_num_w] <= w_data;
        end
    end
    // -------------------------------------------
  end

endmodule

tasks/riscv-task/riscv-task/instruction_memory.sv
module instruction_memory(instruction_address,instruction_data);
  import common_pkg::*;
  output logic [INSTRUCTION_WIDTH - 1 : 0] instruction_data;
  input logic [INSTRUCTION_MEMORY_ADDRESS_WIDTH - 1 : 0] instruction_address;


  reg [INSTRUCTION_WIDTH - 1 : 0] memory [INSTRUCTION_MEMORY_DEPTH];    // 2MB-ish of instruction ROM with 32 bit instructions


  initial begin
    $readmemh("instruction_memory.mem", memory, INSTRUCTION_MEMORY_ADDRESS_WIDTH'('h0), INSTRUCTION_MEMORY_ADDRESS_WIDTH'('hFF));
    $readmemh("instruction_memory.mem", memory, INSTRUCTION_MEMORY_ADDRESS_WIDTH'('h0), INSTRUCTION_MEMORY_ADDRESS_WIDTH'('hFF));

  end

  assign instruction_data = memory[instruction_address];

endmodule

tasks/riscv-task/riscv-task/program_counter.sv
import common_pkg::*;

module program_counter (
  clk,
  rst,

  ALU_zero_flag,
  offset,
  ctrl_branch,

  instruction_address
);

  input   logic   clk;
  input   logic   rst;

  input   logic                                       ALU_zero_flag;
  input   logic signed [RISC_V_DATA_WIDTH - 1 : 0]    offset;
  input   logic                                       ctrl_branch;

  output  logic [INSTRUCTION_MEMORY_ADDRESS_WIDTH - 1 : 0] instruction_address = INSTRUCTION_MEMORY_ADDRESS_WIDTH'('b0);;

  //initial begin
  //    instruction_address = INSTRUCTION_MEMORY_ADDRESS_WIDTH'('b0);
  //end

  always_ff @(posedge clk or posedge rst) begin
    if (rst) begin
      instruction_address <= INSTRUCTION_MEMORY_ADDRESS_WIDTH'('b0);
    end else begin
      if (ALU_zero_flag && ctrl_branch) begin // This line isn't elaborated correctly (works fine in synthesis)? It's possible to trick Vivado using DeMorgan's law
        instruction_address <= instruction_address + (offset[RISC_V_DATA_WIDTH - 1 : 0] << 1);
      end else begin
        instruction_address <= instruction_address + INSTRUCTION_MEMORY_ADDRESS_WIDTH'('b1);
      end
    end
  end


endmodule

tasks/riscv-task/riscv-task/control_unit.sv
import common_pkg::*;

module control_unit (opcode, ctrl_ALU_op, ctrl_ALU_src, ctrl_reg_w, ctrl_mem_w, ctrl_mem_r, ctrl_mem_to_reg, ctrl_branch);

  input   opcode_t    opcode;

  output  reg [1:0] ctrl_ALU_op;
  output  reg       ctrl_ALU_src;
  output  reg       ctrl_reg_w;
  output  reg       ctrl_mem_w;
  output  reg       ctrl_mem_r;
  output  reg       ctrl_mem_to_reg;
  output  reg       ctrl_branch;

  //TODO: set the correct control signals in each state
  always @(*) begin
    case (opcode)
      LOAD:
        begin
          // -------------------------------------------
          ctrl_ALU_op     <= 2'b00;
          ctrl_ALU_src    <= 1'b1;
          ctrl_reg_w      <= 1'b1;
          ctrl_mem_w      <= 1'b0;
          ctrl_mem_r      <= 1'b1;
          ctrl_mem_to_reg <= 1'b1;
          ctrl_branch     <= 1'b0;
          // -------------------------------------------
        end

      STORE:
        begin
          // -------------------------------------------
          ctrl_ALU_op     <= 2'b00;
          ctrl_ALU_src    <= 1'b1;
          ctrl_reg_w      <= 1'b0;
          ctrl_mem_w      <= 1'b1;
          ctrl_mem_r      <= 1'b0;
          ctrl_mem_to_reg <= 1'b0;
          ctrl_branch     <= 1'b0;
          // -------------------------------------------
        end

      ARITH:
        begin
          // -------------------------------------------
          ctrl_ALU_op     <= 2'b10;
          ctrl_ALU_src    <= 1'b0;
          ctrl_reg_w      <= 1'b1;
          ctrl_mem_w      <= 1'b0;
          ctrl_mem_r      <= 1'b0;
          ctrl_mem_to_reg <= 1'b0;
          ctrl_branch     <= 1'b0;
          // -------------------------------------------
        end

      BRANCH:
        begin 
          // -------------------------------------------
          ctrl_ALU_op     <= 2'b01;
          ctrl_ALU_src    <= 1'b0;
          ctrl_reg_w      <= 1'b0;
          ctrl_mem_w      <= 1'b0;
          ctrl_mem_r      <= 1'b0;
          ctrl_mem_to_reg <= 1'b0;
          ctrl_branch     <= 1'b1;
          // -------------------------------------------
        end


      default:
        begin
          ctrl_ALU_op     <= 2'b00;
          ctrl_ALU_src    <= 1'b0;
          ctrl_reg_w      <= 1'b0;
          ctrl_mem_w      <= 1'b0;
          ctrl_mem_r      <= 1'b0;
          ctrl_mem_to_reg <= 1'b0;
          ctrl_branch     <= 1'b0;
        end

    endcase

  end


endmodule

tasks/riscv-task/riscv-task/top_tb.sv
`timescale 1 ns/10 ps  // time-unit = 1 ns, precision = 10 ps
import common_pkg::*;

module top_tb;

  // Simulated IO
  logic           clk;
  logic           rst;
  logic [15:0]    debug;

  // Control lines
  logic [1:0] ctrl_ALU_op;
  logic       ctrl_ALU_src;
  logic       ctrl_reg_w;
  logic       ctrl_mem_w;
  logic       ctrl_mem_r;
  logic       ctrl_mem_to_reg;
  logic       ctrl_branch;

  // Instruction memory
  logic [INSTRUCTION_WIDTH - 1 : 0] instruction;
  logic [INSTRUCTION_MEMORY_ADDRESS_WIDTH - 1 : 0] instruction_address;

  // Register file outputs
  logic [RISC_V_DATA_WIDTH - 1 : 0] reg_read_data_0;
  logic [RISC_V_DATA_WIDTH - 1 : 0] reg_read_data_1;

  // Immediate generator
  logic signed [RISC_V_DATA_WIDTH - 1 : 0] offset;

  // ALU
  ALU_ctrl_t  ALU_ctrl;
  logic [RISC_V_DATA_WIDTH - 1 : 0]   ALU_data_out;
  logic                               ALU_zero_flag;

  // Data Memory
  logic [RISC_V_DATA_WIDTH - 1 : 0] mem_read_data;


  // Simulation Parameters
  localparam half_period = 5;
  localparam period      = half_period * 2;


  // Modules

  control_unit control_unit(
    .opcode(opcode_t'(instruction[6:0])),
    .ctrl_ALU_op(ctrl_ALU_op),
    .ctrl_ALU_src(ctrl_ALU_src),
    .ctrl_reg_w(ctrl_reg_w),
    .ctrl_mem_w(ctrl_mem_w),
    .ctrl_mem_r(ctrl_mem_r),
    .ctrl_mem_to_reg(ctrl_mem_to_reg),
    .ctrl_branch(ctrl_branch));


  program_counter program_counter(
    .clk(clk),
    .rst(rst),

    .ALU_zero_flag(ALU_zero_flag),
    .offset(offset),
    .ctrl_branch(ctrl_branch),

    .instruction_address(instruction_address));


  instruction_memory instruction_memory(
    .instruction_address(instruction_address),
    .instruction_data(instruction));


  register_file register_file(
    .clk(clk),
    .rst(rst),
    .reg_num_r0(instruction[19:15]),
    .reg_num_r1(instruction[24:20]),
    .reg_num_w(instruction[11:7]),
    .r_data_0(reg_read_data_0),
    .r_data_1(reg_read_data_1),
    .w_data(ctrl_mem_to_reg ? mem_read_data : ALU_data_out),
    .ctrl_reg_w(ctrl_reg_w),
    .debug(debug));


  imm_generator imm_generator(
    .instruction(instruction),
    .offset(offset));


  ALU_control ALU_control(
    .funct3(instruction[14:12]),
    .funct7(instruction[31:25]),
    .ALU_ctrl(ALU_ctrl),
    .ctrl_ALU_op(ctrl_ALU_op));


  ALU ALU(
    .data_in_A(reg_read_data_0),
    .data_in_B(ctrl_ALU_src ? offset : reg_read_data_1),
    .data_out(ALU_data_out),
    .zero(ALU_zero_flag),
    .ALU_ctrl(ALU_ctrl));


  data_memory data_memory(
    .clk(clk),
    .rst(rst),
    .w_data(reg_read_data_1),
    .r_data(mem_read_data),
    .address(ALU_data_out[DATA_MEMORY_ADDRESS_WIDTH - 1 : 0]),
    .ctrl_mem_w(ctrl_mem_w),
    .ctrl_mem_r(ctrl_mem_r));

  initial begin
    $dumpfile("dump.vcd");
    $dumpvars(1);
    clk <= 0;
    clk         = 1'b0;
    rst         = 1'b0;

    #period;

    rst         = 1'b1;

    #period;

    rst         = 1'b0;

    #period;
    $display("expected value: 0;    received: %d", debug);

    #period;
    $display("expected value: 1;    received: %d", debug);

    #period;
    #period;
    #period;
    #period;
    #period;
    $display("expected value: 2;    received: %d", debug);

    #period;
    #period;
    #period;
    #period;
    #period;
    $display("expected value: 3;    received: %d", debug);

    #period;
    #period;
    #period;
    #period;
    #period;
    $display("expected value: 5;    received: %d", debug);

    #period;
    #period;
    #period;
    #period;
    #period;
    $display("expected value: 8;    received: %d", debug);

    #period;
    #period;
    #period;
    #period;
    #period;
    $display("expected value: 13;    received: %d", debug);

    #period;
    #period;
    #period;
    #period;
    #period;
    $display("expected value: 21;    received: %d", debug);


    #period;
    #period;
    #period;
    #period;
    #period;
    $display("expected value: 34;    received: %d", debug);

    #period;
    #period;
    #period;
    #period;
    #period;
    $display("expected value: 55;    received: %d", debug);

    #1000 $finish;

  end

  always
    #half_period clk = !clk;

endmodule

tasks/riscv-task/riscv-task/clock_divider.sv
module clock_divider (

  clk_in,
  rst,
  clk_out
);
  import common_pkg::*;

  input   logic clk_in;
  input   logic rst;
  output  logic clk_out;

  logic [27:0] counter; // The basys3 clock is 200MHZ so it should never need to count higher than 28 bits

  initial begin
    counter = 28'd0;
  end

  always @(posedge clk_in or posedge rst)
    begin
      if(rst) begin
        counter <= 28'd0;
      end else begin
        counter <= counter + 28'd1;
        if(counter >= (CLOCK_DIVISOR - 1))
          counter <= 28'd0;
      end

      clk_out <= (counter < CLOCK_DIVISOR / 2) ? 1'b1 : 1'b0;
    end

endmodule

tasks/riscv-task/riscv-task/top.sv
import common_pkg::*;

module top (
  clk_200M,
  rst,
  debug
);

  //IO
  input   logic           clk_200M;
  input   logic           rst;
  output  logic [15:0]    debug;


  // Clock Divider
  logic clk;

  // Control lines
  logic [1:0] ctrl_ALU_op;
  logic       ctrl_ALU_src;
  logic       ctrl_reg_w;
  logic       ctrl_mem_w;
  logic       ctrl_mem_r;
  logic       ctrl_mem_to_reg;
  logic       ctrl_branch;

  // Instruction memory
  logic [INSTRUCTION_WIDTH - 1 : 0] instruction;
  logic [INSTRUCTION_MEMORY_ADDRESS_WIDTH - 1 : 0] instruction_address;

  // Register file outputs
  logic [RISC_V_DATA_WIDTH - 1 : 0] reg_read_data_0;
  logic [RISC_V_DATA_WIDTH - 1 : 0] reg_read_data_1;

  // Immediate generator
  logic signed [RISC_V_DATA_WIDTH - 1 : 0] offset;

  // ALU
  ALU_ctrl_t  ALU_ctrl;
  logic [RISC_V_DATA_WIDTH - 1 : 0]   ALU_data_out;
  logic                               ALU_zero_flag;

  // Data Memory
  logic [RISC_V_DATA_WIDTH - 1 : 0] mem_read_data;


  // Modules
  clock_divider clock_divider(
    .clk_in(clk_200M),
    .rst(rst),
    .clk_out(clk));


  control_unit control_unit(
    .opcode(opcode_t'(instruction[6:0])),
    .ctrl_ALU_op(ctrl_ALU_op),
    .ctrl_ALU_src(ctrl_ALU_src),
    .ctrl_reg_w(ctrl_reg_w),
    .ctrl_mem_w(ctrl_mem_w),
    .ctrl_mem_r(ctrl_mem_r),
    .ctrl_mem_to_reg(ctrl_mem_to_reg),
    .ctrl_branch(ctrl_branch));


  program_counter program_counter(
    .clk(clk),
    .rst(rst),

    .ALU_zero_flag(ALU_zero_flag),
    .offset(offset),
    .ctrl_branch(ctrl_branch),

    .instruction_address(instruction_address));


  instruction_memory instruction_memory(
    .instruction_address(instruction_address),
    .instruction_data(instruction));


  register_file register_file(
    .clk(clk),
    .rst(rst),
    .reg_num_r0(instruction[19:15]),
    .reg_num_r1(instruction[24:20]),
    .reg_num_w(instruction[11:7]),
    .r_data_0(reg_read_data_0),
    .r_data_1(reg_read_data_1),
    .w_data(ctrl_mem_to_reg ? mem_read_data : ALU_data_out),
    .ctrl_reg_w(ctrl_reg_w),
    .debug(debug));


  imm_generator imm_generator(
    .instruction(instruction),
    .offset(offset));


  ALU_control ALU_control(
    .funct3(instruction[14:12]),
    .funct7(instruction[31:25]),
    .ALU_ctrl(ALU_ctrl),
    .ctrl_ALU_op(ctrl_ALU_op));


  ALU ALU(
    .data_in_A(reg_read_data_0),
    .data_in_B(ctrl_ALU_src ? offset : reg_read_data_1),
    .data_out(ALU_data_out),
    .zero(ALU_zero_flag),
    .ALU_ctrl(ALU_ctrl));


  data_memory data_memory(
    .clk(clk),
    .rst(rst),
    .w_data(reg_read_data_1),
    .r_data(mem_read_data),
    .address(ALU_data_out[DATA_MEMORY_ADDRESS_WIDTH - 1 : 0]),
    .ctrl_mem_w(ctrl_mem_w),
    .ctrl_mem_r(ctrl_mem_r));


endmodule

tasks/riscv-task/riscv-task/dump.vcd
$date
	Mon Feb 16 17:54:14 2026
$end
$version
	Icarus Verilog
$end
$timescale
	10ps
$end
$scope module top $end
$var wire 1 ! clk_200M $end
$var wire 1 " rst $end
$var wire 64 # reg_read_data_1 [63:0] $end
$var wire 64 $ reg_read_data_0 [63:0] $end
$var wire 64 % offset [63:0] $end
$var wire 64 & mem_read_data [63:0] $end
$var wire 8 ' instruction_address [7:0] $end
$var wire 32 ( instruction [31:0] $end
$var wire 16 ) debug [15:0] $end
$var wire 1 * ctrl_reg_w $end
$var wire 1 + ctrl_mem_w $end
$var wire 1 , ctrl_mem_to_reg $end
$var wire 1 - ctrl_mem_r $end
$var wire 1 . ctrl_branch $end
$var wire 1 / ctrl_ALU_src $end
$var wire 2 0 ctrl_ALU_op [1:0] $end
$var wire 1 1 clk $end
$var wire 1 2 ALU_zero_flag $end
$var wire 64 3 ALU_data_out [63:0] $end
$var wire 3 4 ALU_ctrl [2:0] $end
$upscope $end
$scope module top_tb $end
$var wire 64 5 reg_read_data_1 [63:0] $end
$var wire 64 6 reg_read_data_0 [63:0] $end
$var wire 64 7 offset [63:0] $end
$var wire 64 8 mem_read_data [63:0] $end
$var wire 8 9 instruction_address [7:0] $end
$var wire 32 : instruction [31:0] $end
$var wire 16 ; debug [15:0] $end
$var wire 1 < ctrl_reg_w $end
$var wire 1 = ctrl_mem_w $end
$var wire 1 > ctrl_mem_to_reg $end
$var wire 1 ? ctrl_mem_r $end
$var wire 1 @ ctrl_branch $end
$var wire 1 A ctrl_ALU_src $end
$var wire 2 B ctrl_ALU_op [1:0] $end
$var wire 1 C ALU_zero_flag $end
$var wire 64 D ALU_data_out [63:0] $end
$var wire 3 E ALU_ctrl [2:0] $end
$var parameter 32 F half_period $end
$var parameter 64 G period $end
$var reg 1 H clk $end
$var reg 1 I rst $end
$upscope $end
$enddefinitions $end
$comment Show the parameter values. $end
$dumpall
b1010 G
b101 F
$end
#0
$dumpvars
0I
0H
b10 E
b100001 D
0C
b0 B
1A
0@
1?
1>
0=
1<
b0 ;
b10000100000011000010000011 :
b0 9
b1 8
b100001 7
b0 6
b0 5
b10 4
b100001 3
02
x1
b0 0
1/
0.
1-
1,
0+
1*
b0 )
b10000100000011000010000011 (
b0 '
b1 &
b100001 %
b0 $
b0 #
z"
z!
$end
#500
0>
0?
0A
b10 B
b0 8
0C
b1 D
b0 7
b100000000111110110011 :
b1 9
b1 5
1H
#1000
b1 8
1>
1?
1A
b0 B
0C
b100001 D
b100001 7
b10 E
b0 5
b10000100000011000010000011 :
b0 9
0H
1I
#1500
1H
#2000
0H
0I
#2500
0>
0?
0A
b10 B
b0 8
0C
b1 D
b0 7
b1 5
b100000000111110110011 :
b1 9
1H
#3000
0H
#3500
b1 D
b0 5
b1 6
b1 ;
b1000001000000000110011 :
b10 9
1H
#4000
0H
#4500
b1011111000000010110011 :
b11 9
1H
#5000
0H
#5500
b100 9
1H
#6000
0H
#6500
1C
b0 D
1@
0<
b1 B
b1111111111111111111111111111111111111111111111111111111111111110 7
b110 E
b1 5
b11111110000000000000111011100011 :
b101 9
1H
#7000
0H
#7500
0C
b10 D
b10 E
0@
1<
b10 B
b0 7
b100000000111110110011 :
b1 9
1H
#8000
0H
#8500
b1 D
b10 ;
b0 5
b1000001000000000110011 :
b10 9
1H
#9000
0H
#9500
b10 D
b10 6
b1011111000000010110011 :
b11 9
1H
#10000
0H
#10500
b100 9
1H
#11000
0H
#11500
1C
1@
0<
b1 B
b1111111111111111111111111111111111111111111111111111111111111110 7
b110 E
b0 D
b1 5
b1 6
b11111110000000000000111011100011 :
b101 9
1H
#12000
0H
#12500
b10 E
0@
1<
b10 B
0C
b11 D
b10 5
b0 7
b100000000111110110011 :
b1 9
1H
#13000
0H
#13500
b10 D
b0 5
b10 6
b11 ;
b1000001000000000110011 :
b10 9
1H
#14000
0H
#14500
b11 D
b11 6
b1011111000000010110011 :
b11 9
1H
#15000
0H
#15500
b100 9
1H
#16000
0H
#16500
1C
1@
0<
b1 B
b1111111111111111111111111111111111111111111111111111111111111110 7
b110 E
b0 D
b10 5
b10 6
b11111110000000000000111011100011 :
b101 9
1H
#17000
0H
#17500
b10 E
0@
1<
b10 B
0C
b101 D
b11 5
b0 7
b100000000111110110011 :
b1 9
1H
#18000
0H
#18500
b11 D
b101 ;
b0 5
b11 6
b1000001000000000110011 :
b10 9
1H
#19000
0H
#19500
b101 D
b101 6
b1011111000000010110011 :
b11 9
1H
#20000
0H
#20500
b100 9
1H
#21000
0H
#21500
1C
1@
0<
b1 B
b1111111111111111111111111111111111111111111111111111111111111110 7
b110 E
b0 D
b11 5
b11 6
b11111110000000000000111011100011 :
b101 9
1H
#22000
0H
#22500
b10 E
0@
1<
b10 B
0C
b1000 D
b101 5
b0 7
b100000000111110110011 :
b1 9
1H
#23000
0H
#23500
b101 D
b0 5
b101 6
b1000 ;
b1000001000000000110011 :
b10 9
1H
#24000
0H
#24500
b1000 D
b1000 6
b1011111000000010110011 :
b11 9
1H
#25000
0H
#25500
b100 9
1H
#26000
0H
#26500
1C
1@
0<
b1 B
b1111111111111111111111111111111111111111111111111111111111111110 7
b110 E
b0 D
b101 5
b101 6
b11111110000000000000111011100011 :
b101 9
1H
#27000
0H
#27500
b10 E
0@
1<
b10 B
0C
b1101 D
b1000 5
b0 7
b100000000111110110011 :
b1 9
1H
#28000
0H
#28500
b1000 D
b1101 ;
b0 5
b1000 6
b1000001000000000110011 :
b10 9
1H
#29000
0H
#29500
b1101 D
b1101 6
b1011111000000010110011 :
b11 9
1H
#30000
0H
#30500
b100 9
1H
#31000
0H
#31500
1C
1@
0<
b1 B
b1111111111111111111111111111111111111111111111111111111111111110 7
b110 E
b0 D
b1000 5
b1000 6
b11111110000000000000111011100011 :
b101 9
1H
#32000
0H
#32500
b10 E
0@
1<
b10 B
0C
b10101 D
b1101 5
b0 7
b100000000111110110011 :
b1 9
1H
#33000
0H
#33500
b1101 D
b0 5
b1101 6
b10101 ;
b1000001000000000110011 :
b10 9
1H
#34000
0H
#34500
b10101 D
b10101 6
b1011111000000010110011 :
b11 9
1H
#35000
0H
#35500
b100 9
1H
#36000
0H
#36500
1C
1@
0<
b1 B
b1111111111111111111111111111111111111111111111111111111111111110 7
b110 E
b0 D
b1101 5
b1101 6
b11111110000000000000111011100011 :
b101 9
1H
#37000
0H
#37500
b10 E
0@
1<
b10 B
0C
b100010 D
b10101 5
b0 7
b100000000111110110011 :
b1 9
1H
#38000
0H
#38500
b10101 D
b100010 ;
b0 5
b10101 6
b1000001000000000110011 :
b10 9
1H
#39000
0H
#39500
b100010 D
b100010 6
b1011111000000010110011 :
b11 9
1H
#40000
0H
#40500
b100 9
1H
#41000
0H
#41500
1C
1@
0<
b1 B
b1111111111111111111111111111111111111111111111111111111111111110 7
b110 E
b0 D
b10101 5
b10101 6
b11111110000000000000111011100011 :
b101 9
1H
#42000
0H
#42500
b10 E
0@
1<
b10 B
0C
b110111 D
b100010 5
b0 7
b100000000111110110011 :
b1 9
1H
#43000
0H
#43500
b100010 D
b0 5
b100010 6
b110111 ;
b1000001000000000110011 :
b10 9
1H
#44000
0H
#44500
b110111 D
b110111 6
b1011111000000010110011 :
b11 9
1H
#45000
0H
#45500
b100 9
1H
#46000
0H
#46500
1C
1@
0<
b1 B
b1111111111111111111111111111111111111111111111111111111111111110 7
b110 E
b0 D
b100010 5
b100010 6
b11111110000000000000111011100011 :
b101 9
1H
#47000
0H
#47500
b10 E
0@
1<
b10 B
0C
b1011001 D
b110111 5
b0 7
b100000000111110110011 :
b1 9
1H
#48000
0H
#48500
b110111 D
b1011001 ;
b0 5
b110111 6
b1000001000000000110011 :
b10 9
1H
#49000
0H
#49500
b1011001 D
b1011001 6
b1011111000000010110011 :
b11 9
1H
#50000
0H
#50500
b100 9
1H
#51000
0H
#51500
1C
1@
0<
b1 B
b1111111111111111111111111111111111111111111111111111111111111110 7
b110 E
b0 D
b110111 5
b110111 6
b11111110000000000000111011100011 :
b101 9
1H
#52000
0H
#52500
b10 E
0@
1<
b10 B
0C
b10010000 D
b1011001 5
b0 7
b100000000111110110011 :
b1 9
1H
#53000
0H
#53500
b1011001 D
b0 5
b1011001 6
b10010000 ;
b1000001000000000110011 :
b10 9
1H
#54000
0H
#54500
b10010000 D
b10010000 6
b1011111000000010110011 :
b11 9
1H
#55000
0H
#55500
b100 9
1H
#56000
0H
#56500
1C
1@
0<
b1 B
b1111111111111111111111111111111111111111111111111111111111111110 7
b110 E
b0 D
b1011001 5
b1011001 6
b11111110000000000000111011100011 :
b101 9
1H
#57000
0H
#57500
b10 E
0@
1<
b10 B
0C
b11101001 D
b10010000 5
b0 7
b100000000111110110011 :
b1 9
1H
#58000
0H
#58500
b10010000 D
b11101001 ;
b0 5
b10010000 6
b1000001000000000110011 :
b10 9
1H
#59000
0H
#59500
b11101001 D
b11101001 6
b1011111000000010110011 :
b11 9
1H
#60000
0H
#60500
b100 9
1H
#61000
0H
#61500
1C
1@
0<
b1 B
b1111111111111111111111111111111111111111111111111111111111111110 7
b110 E
b0 D
b10010000 5
b10010000 6
b11111110000000000000111011100011 :
b101 9
1H
#62000
0H
#62500
b10 E
0@
1<
b10 B
0C
b101111001 D
b11101001 5
b0 7
b100000000111110110011 :
b1 9
1H
#63000
0H
#63500
b11101001 D
b0 5
b11101001 6
b101111001 ;
b1000001000000000110011 :
b10 9
1H
#64000
0H
#64500
b101111001 D
b101111001 6
b1011111000000010110011 :
b11 9
1H
#65000
0H
#65500
b100 9
1H
#66000
0H
#66500
1C
1@
0<
b1 B
b1111111111111111111111111111111111111111111111111111111111111110 7
b110 E
b0 D
b11101001 5
b11101001 6
b11111110000000000000111011100011 :
b101 9
1H
#67000
0H
#67500
b10 E
0@
1<
b10 B
0C
b1001100010 D
b101111001 5
b0 7
b100000000111110110011 :
b1 9
1H
#68000
0H
#68500
b101111001 D
b1001100010 ;
b0 5
b101111001 6
b1000001000000000110011 :
b10 9
1H
#69000
0H
#69500
b1001100010 D
b1001100010 6
b1011111000000010110011 :
b11 9
1H
#70000
0H
#70500
b100 9
1H
#71000
0H
#71500
1C
1@
0<
b1 B
b1111111111111111111111111111111111111111111111111111111111111110 7
b110 E
b0 D
b101111001 5
b101111001 6
b11111110000000000000111011100011 :
b101 9
1H
#72000
0H
#72500
b10 E
0@
1<
b10 B
0C
b1111011011 D
b1001100010 5
b0 7
b100000000111110110011 :
b1 9
1H
#73000
0H
#73500
b1001100010 D
b0 5
b1001100010 6
b1111011011 ;
b1000001000000000110011 :
b10 9
1H
#74000
0H
#74500
b1111011011 D
b1111011011 6
b1011111000000010110011 :
b11 9
1H
#75000
0H
#75500
b100 9
1H
#76000
0H
#76500
1C
1@
0<
b1 B
b1111111111111111111111111111111111111111111111111111111111111110 7
b110 E
b0 D
b1001100010 5
b1001100010 6
b11111110000000000000111011100011 :
b101 9
1H
#77000
0H
#77500
b10 E
0@
1<
b10 B
0C
b11000111101 D
b1111011011 5
b0 7
b100000000111110110011 :
b1 9
1H
#78000
0H
#78500
b1111011011 D
b11000111101 ;
b0 5
b1111011011 6
b1000001000000000110011 :
b10 9
1H
#79000
0H
#79500
b11000111101 D
b11000111101 6
b1011111000000010110011 :
b11 9
1H
#80000
0H
#80500
b100 9
1H
#81000
0H
#81500
1C
1@
0<
b1 B
b1111111111111111111111111111111111111111111111111111111111111110 7
b110 E
b0 D
b1111011011 5
b1111011011 6
b11111110000000000000111011100011 :
b101 9
1H
#82000
0H
